solana_live/__init__.py
solana_live/markets.py
solana_live-0.1.0.dist-info/METADATA
solana_live-0.1.0.dist-info/WHEEL
solana_live-0.1.0.dist-info/top_level.txt
solana_live-0.1.0.dist-info/RECORD
