Metadata-Version: 2.4
Name: solana_live
Version: 0.1.0
Summary: This Python library provides utilities to fetch token prices from decentralized exchanges (DEXs) across Ethereum and Solana networks. It uses Web3.py for Ethereum and the Solders library for Solana, along with other utilities to interact with DEXs like Uniswap, Sushiswap, Pancakeswap (Ethereum), and Serum (Solana).
Classifier: Programming Language :: Python :: 3
Classifier: Operating System :: OS Independent
Requires-Python: >=3.9
Requires-Dist: requests
Requires-Dist: base58
Requires-Dist: web3
Requires-Dist: solana
Requires-Dist: solders
